gridy/__init__.py
gridy/constants.py
gridy/extractTable1.py
gridy/pdfExtractionUtils.py
gridy/utils.py
gridy/wrapp.py
gridy-0.1.2.dist-info/METADATA
gridy-0.1.2.dist-info/WHEEL
gridy-0.1.2.dist-info/RECORD
