Metadata-Version: 2.1
Name: gridy
Version: 0.1.2
Summary: Identify grids
License: MIT
Author: Polyhedron
Requires-Python: >=3.10,<4.0
Classifier: License :: OSI Approved :: MIT License
Classifier: Programming Language :: Python :: 3
Classifier: Programming Language :: Python :: 3.10
Classifier: Programming Language :: Python :: 3.11
Requires-Dist: Pillow (>=10.0.0,<11.0.0)
Requires-Dist: lxml (>=4.9.3,<5.0.0)
Requires-Dist: opencv-python (>=4.8.0.74,<5.0.0.0)
Requires-Dist: pandas (>=2.0.0,<3.0.0)
